phishdetect_admin-5.3.0.data/scripts/phishdetect-admin
phishdetectadmin/__init__.py
phishdetectadmin/app.py
phishdetectadmin/config.py
phishdetectadmin/session.py
phishdetectadmin/utils.py
phishdetectadmin/__pycache__/__init__.cpython-38.pyc
phishdetectadmin/__pycache__/__init__.cpython-39.pyc
phishdetectadmin/__pycache__/app.cpython-38.pyc
phishdetectadmin/__pycache__/app.cpython-39.pyc
phishdetectadmin/__pycache__/config.cpython-38.pyc
phishdetectadmin/__pycache__/config.cpython-39.pyc
phishdetectadmin/__pycache__/session.cpython-38.pyc
phishdetectadmin/__pycache__/session.cpython-39.pyc
phishdetectadmin/__pycache__/utils.cpython-38.pyc
phishdetectadmin/__pycache__/utils.cpython-39.pyc
phishdetectadmin/css/main.css
phishdetectadmin/css/main.dist.css
phishdetectadmin/js/jquery-3.5.1.min.js
phishdetectadmin/templates/alerts.html
phishdetectadmin/templates/conf.html
phishdetectadmin/templates/error.html
phishdetectadmin/templates/indicators_add.html
phishdetectadmin/templates/indicators_controls.html
phishdetectadmin/templates/indicators_list.html
phishdetectadmin/templates/indicators_view.html
phishdetectadmin/templates/layout.html
phishdetectadmin/templates/node.html
phishdetectadmin/templates/report.html
phishdetectadmin/templates/reports.html
phishdetectadmin/templates/success.html
phishdetectadmin/templates/users_active.html
phishdetectadmin/templates/users_pending.html
phishdetect_admin-5.3.0.dist-info/LICENSE
phishdetect_admin-5.3.0.dist-info/METADATA
phishdetect_admin-5.3.0.dist-info/WHEEL
phishdetect_admin-5.3.0.dist-info/top_level.txt
phishdetect_admin-5.3.0.dist-info/RECORD
