Metadata-Version: 2.1
Name: phishdetect-admin
Version: 5.3.0
Summary: Web application to administer a PhishDetect Node
Home-page: UNKNOWN
Author: Claudio Guarnieri
Author-email: nex@nex.sx
License: GPLv3
Keywords: security phishing phishdetect
Platform: UNKNOWN
Requires-Dist: Flask
Requires-Dist: PyYAML
Requires-Dist: flask-wtf
Requires-Dist: phishdetect (>=1.10.0)
Requires-Dist: requests
